transitle/__init__.py
transitle/__main__.py
transitle/translator.py
transitle/ts.py
translate_subtitles-1.1.1.dist-info/LICENSE
translate_subtitles-1.1.1.dist-info/METADATA
translate_subtitles-1.1.1.dist-info/WHEEL
translate_subtitles-1.1.1.dist-info/entry_points.txt
translate_subtitles-1.1.1.dist-info/top_level.txt
translate_subtitles-1.1.1.dist-info/RECORD
